<?xml version="1.0" encoding="utf-8" ?>
<dwsync>
<file name="bg-a-3.gif" server="//Server2003/virtuals/paypal.alternativa.des/" local="128685654350000000" remote="128685654350000000" />
<file name="bg-caja-sombra.gif" server="//Server2003/virtuals/paypal.alternativa.des/" local="128685582520000000" remote="128685582520000000" />
<file name="bg-content-bot.gif" server="//Server2003/virtuals/paypal.alternativa.des/" local="128684848980000000" remote="128684848980000000" />
<file name="bg-content-top.gif" server="//Server2003/virtuals/paypal.alternativa.des/" local="128684848980000000" remote="128684848980000000" />
<file name="bg-content.gif" server="//Server2003/virtuals/paypal.alternativa.des/" local="128684848980000000" remote="128684848980000000" />
<file name="bg-home.jpg" server="//Server2003/virtuals/paypal.alternativa.des/" local="128685594380000000" remote="128685594380000000" />
<file name="borrar-home.jpg" server="//Server2003/virtuals/paypal.alternativa.des/" local="128685604070000000" remote="128685604070000000" />
<file name="bottom-botonera.gif" server="//Server2003/virtuals/paypal.alternativa.des/" local="128703774177187500" remote="128703774170000000" />
<file name="curvita-top.gif" server="//Server2003/virtuals/paypal.alternativa.des/" local="128703774182031250" remote="128703774180000000" />
<file name="menu-1-over.gif" server="//Server2003/virtuals/paypal.alternativa.des/" local="128685632620000000" remote="128685632620000000" />
<file name="quote.gif" server="//Server2003/virtuals/paypal.alternativa.des/" local="128703774162968750" remote="128703774160000000" />
<file name="quote_footer.gif" server="//Server2003/virtuals/paypal.alternativa.des/" local="128703774167656250" remote="128703774160000000" />
<file name="quote_header.gif" server="//Server2003/virtuals/paypal.alternativa.des/" local="128703774172187500" remote="128703774170000000" />
<file name="reportes.jpg" server="//Server2003/virtuals/paypal.alternativa.des/" local="128685615520000000" remote="128685615520000000" />
<file name="tit-bienvenido.gif" server="//Server2003/virtuals/paypal.alternativa.des/" local="128685579270000000" remote="128685579270000000" />
<file name="top-botonera.gif" server="//Server2003/virtuals/paypal.alternativa.des/" local="128703774191875000" remote="128703774190000000" />
<file name="bg-link-activo.gif" server="//Server2003/virtuals/paypal.alternativa.des/" local="128708903289531250" remote="128708903280000000" />
</dwsync>